{
  "by" : "avar",
  "id" : 15879087,
  "kids" : [ 15879330 ],
  "parent" : 15878964,
  "text" : "<p><pre><code>    &gt; The top 1000 holders of gold\n    &gt; don&#x27;t have anywhere near 40%\n    &gt; of the market.\n</code></pre>\nYou&#x27;re right, they have a lot more than that. Total world gold reserves are around 30K tons. The US alone has 8K tons, Germany 3K, IMF 3K, Italy 2.5K etc.<p>So just the to 2 holders of Gold have almost 40% of the market, and the top 10 have 80%.<p>1. <a href=\"https:&#x2F;&#x2F;en.wikipedia.org&#x2F;wiki&#x2F;Gold_reserve\" rel=\"nofollow\">https:&#x2F;&#x2F;en.wikipedia.org&#x2F;wiki&#x2F;Gold_reserve</a>",
  "time" : 1512745598,
  "type" : "comment"
}
