{
  "by" : "avar",
  "id" : 5933274,
  "kids" : [ 5933571 ],
  "parent" : 5933175,
  "text" : "<p><pre><code>    &gt; Ecuador too of all countries is taking an anti-US stance. It&#x27;s a\n    &gt; strange country to claim to be supporting human rights\n</code></pre>\nIf you&#x27;re already on unfriendly terms with the U.S. it would seem to\nbe in your interest to undermine them and cast them in a bad light.<p>You don&#x27;t need noble intentions to score political points by accepting\na high-profile refugee fleeing from a government largely hostile to\nyou.",
  "time" : 1372085602,
  "type" : "comment"
}
